configger/__init__.py
configger/config.py
configger/constants.py
configger-0.0.1.dist-info/LICENSE
configger-0.0.1.dist-info/METADATA
configger-0.0.1.dist-info/WHEEL
configger-0.0.1.dist-info/top_level.txt
configger-0.0.1.dist-info/RECORD
