Metadata-Version: 2.1
Name: configger
Version: 0.0.1
Summary: Simple config
Home-page: https://github.com/paulharter/configger.git
Author: Paul Harter
Author-email: paul@glowinthedark.co.uk
License: LICENSE
Platform: UNKNOWN
